opentelemetry/exporter/otlp/py.typed
opentelemetry/exporter/otlp/version.py
opentelemetry_exporter_otlp_custom-1.15.0.dist-info/METADATA
opentelemetry_exporter_otlp_custom-1.15.0.dist-info/WHEEL
opentelemetry_exporter_otlp_custom-1.15.0.dist-info/entry_points.txt
opentelemetry_exporter_otlp_custom-1.15.0.dist-info/licenses/LICENSE
opentelemetry_exporter_otlp_custom-1.15.0.dist-info/RECORD
